cpppo/__init__.py
cpppo/automata.py
cpppo/automata_test.py
cpppo/dotdict.py
cpppo/dotdict_test.py
cpppo/history_test.py
cpppo/misc.py
cpppo/misc_test.py
cpppo/modbus_test.py
cpppo/multiprocessing_test.py
cpppo/readme.py
cpppo/remote_test.py
cpppo/serial_test.py
cpppo/ttyV-setup.py
cpppo/version.py
cpppo/bin/__init__.py
cpppo/bin/modbus_poll.py
cpppo/bin/modbus_sim.py
cpppo/history/__init__.py
cpppo/history/files.py
cpppo/history/times.py
cpppo/remote/__init__.py
cpppo/remote/io.py
cpppo/remote/plc.py
cpppo/remote/plc_modbus.py
cpppo/remote/pymodbus_fixes.py
cpppo/server/__init__.py
cpppo/server/echo.py
cpppo/server/echo_test.py
cpppo/server/enip_test.py
cpppo/server/logix_test.py
cpppo/server/network.py
cpppo/server/network_test.py
cpppo/server/tnet.py
cpppo/server/tnet_test.py
cpppo/server/tnetraw.py
cpppo/server/tnetstrings.py
cpppo/server/tnetstrings_test.py
cpppo/server/enip/__init__.py
cpppo/server/enip/__main__.py
cpppo/server/enip/ab.py
cpppo/server/enip/client.py
cpppo/server/enip/client_test.py
cpppo/server/enip/defaults.py
cpppo/server/enip/device.py
cpppo/server/enip/get_attribute.py
cpppo/server/enip/hart.py
cpppo/server/enip/hart_test.py
cpppo/server/enip/historize.py
cpppo/server/enip/io_example.py
cpppo/server/enip/list_identity_backplane.py
cpppo/server/enip/list_identity_simple.py
cpppo/server/enip/list_services.py
cpppo/server/enip/logix.py
cpppo/server/enip/main.py
cpppo/server/enip/open_example.py
cpppo/server/enip/parser.py
cpppo/server/enip/parser_test.py
cpppo/server/enip/pccc.py
cpppo/server/enip/poll.py
cpppo/server/enip/poll_example.py
cpppo/server/enip/poll_example_clogix.py
cpppo/server/enip/poll_example_many.py
cpppo/server/enip/poll_example_many_with_write.py
cpppo/server/enip/poll_example_simple.py
cpppo/server/enip/poll_test.py
cpppo/server/enip/powerflex_motor_velocity.py
cpppo/server/enip/simulator_example.py
cpppo/server/enip/thruput.py
cpppo/server/enip/ucmm.py
cpppo/server/enip/udt.py
cpppo/server/enip/udt_test.py
cpppo-5.2.5.dist-info/COPYING
cpppo-5.2.5.dist-info/LICENSE
cpppo-5.2.5.dist-info/METADATA
cpppo-5.2.5.dist-info/WHEEL
cpppo-5.2.5.dist-info/entry_points.txt
cpppo-5.2.5.dist-info/top_level.txt
cpppo-5.2.5.dist-info/RECORD
